alembic/__init__.py
alembic/env.py
alembic/versions/0c554ca8cb51_add_renamed_columns_for_timescaledb_.py
alembic/versions/0f19c76c2458_restore_missing_indices_and_constraints_.py
alembic/versions/136d2c0ff764_init_schema.py
alembic/versions/1541fb9cfe23_recreate_time_sku_features_table.py
alembic/versions/1a0b9cd19b31_create_complete_schema_for_new_database.py
alembic/versions/38b3af57ca90_migration_temporary_test_20251015_235048.py
alembic/versions/3fa4e62e787b_update_schema_changes_renamed_index_and_.py
alembic/versions/4da94c2facf0_add_flags_table.py
alembic/versions/51adc521f5d4_update_column_types.py
alembic/versions/5df859d3bc55_rename_quantity_columns_to_quantity.py
alembic/versions/70db459055a2_migration_master_test_db_20251005_140057.py
alembic/versions/9f2dac16ce3b_add_missing_unique_constraints.py
alembic/versions/c19fab5a6d53_update_schema_from_fresh_master_test_.py
alembic/versions/c314c0e2becc_recreate_tables_with_correct_column_.py
alembic/versions/c76cf026488e_add_orderintakedaily_deliveriesbyday_.py
alembic/versions/d2470bbb912d_remove_redundant_indices_from_time_.py
alembic/versions/fresh_db_bootstrap_20250921.py
alembic/versions/fresh_master_test_init_20250930.py
alembic/versions/new_empty_db_init.py
archive/alembic/__init__.py
archive/alembic/env.py
build/lib/alembic/__init__.py
build/lib/alembic/env.py
build/lib/alembic/versions/0c554ca8cb51_add_renamed_columns_for_timescaledb_.py
build/lib/alembic/versions/0f19c76c2458_restore_missing_indices_and_constraints_.py
build/lib/alembic/versions/136d2c0ff764_init_schema.py
build/lib/alembic/versions/1541fb9cfe23_recreate_time_sku_features_table.py
build/lib/alembic/versions/1a0b9cd19b31_create_complete_schema_for_new_database.py
build/lib/alembic/versions/38b3af57ca90_migration_temporary_test_20251015_235048.py
build/lib/alembic/versions/3fa4e62e787b_update_schema_changes_renamed_index_and_.py
build/lib/alembic/versions/4da94c2facf0_add_flags_table.py
foundry_sdk-0.0.279.dist-info/licenses/LICENSE
foundry_sdk-0.0.279.dist-info/METADATA
foundry_sdk-0.0.279.dist-info/WHEEL
foundry_sdk-0.0.279.dist-info/top_level.txt
foundry_sdk-0.0.279.dist-info/RECORD
