Metadata-Version: 2.4
Name: foundry-sdk
Version: 0.0.279
Summary: A collection of tools and utilities for ETL and training pipelines
Author-email: D3 Group <contact@d3group.com>
Maintainer-email: D3 Group <contact@d3group.com>
License-Expression: MIT
Requires-Python: >=3.12
License-File: LICENSE
Requires-Dist: pandas>=1.5.0
Requires-Dist: numpy>=1.21.0
Requires-Dist: kedro>=1.0.0
Requires-Dist: kedro-viz>=10.0.0
Requires-Dist: kedro-datasets>=6.0.0
Requires-Dist: sqlalchemy>=2.0.30
Requires-Dist: psycopg2-binary
Requires-Dist: polars
Requires-Dist: tqdm
Provides-Extra: dev
Requires-Dist: pytest; extra == "dev"
Requires-Dist: ruff; extra == "dev"
Requires-Dist: mypy; extra == "dev"
Dynamic: license-file
